codelock/__init__.py
codelock/cdcli.py
Codelock_dev-2.dist-info/LICENSE.txt
Codelock_dev-2.dist-info/METADATA
Codelock_dev-2.dist-info/WHEEL
Codelock_dev-2.dist-info/entry_points.txt
Codelock_dev-2.dist-info/top_level.txt
Codelock_dev-2.dist-info/RECORD
