Metadata-Version: 2.1
Name: Codelock-dev
Version: 2
Summary: CodeLock Official CLI for the development environment
Home-page: UNKNOWN
Author: Codelock
License: MIT
Keywords: codelock,cli
Platform: UNKNOWN
Classifier: Development Status :: 2 - Pre-Alpha
Classifier: Intended Audience :: Developers
Classifier: Topic :: Utilities
Classifier: License :: OSI Approved :: MIT License
Classifier: Programming Language :: Python :: 3.7
Classifier: Programming Language :: Python :: 3.8
Classifier: Programming Language :: Python :: 3.9
Classifier: Programming Language :: Python :: 3.10
License-File: LICENSE.txt
Requires-Dist: requests (>=2.28.1)
Requires-Dist: tk
Provides-Extra: dev
Requires-Dist: shutil ; extra == 'dev'
Requires-Dist: requests ; extra == 'dev'
Requires-Dist: tk ; extra == 'dev'
